TST5/__init__.py
tst5-0.1.0.dist-info/METADATA
tst5-0.1.0.dist-info/WHEEL
tst5-0.1.0.dist-info/top_level.txt
tst5-0.1.0.dist-info/RECORD
