Metadata-Version: 2.4
Name: TST5
Version: 0.1.0
Summary: Minimal library for TimeST5 time series instruction model inference
Author: Konstantin
Author-email: konstphx@gmail.com
Requires-Python: >=3.8
Requires-Dist: torch>=1.13.0
Requires-Dist: transformers>=4.25.0
Requires-Dist: numpy>=1.21.0
Requires-Dist: safetensors>=0.3.0
Requires-Dist: huggingface_hub>=0.15.0
Dynamic: author
Dynamic: author-email
Dynamic: requires-dist
Dynamic: requires-python
Dynamic: summary
